{"channeldata_version":1,"packages":{"mirtk":{"activate.d":false,"binary_prefix":true,"deactivate.d":false,"description":"MIRTK is a research-focused image registration and processing toolkit for medical imaging, supporting rigid, affine, and non-rigid registration. This build includes the image viewer (iviewer) on Linux.","home":"https://github.com/BioMedIA/MIRTK","license":"Apache-2.0","post_link":false,"pre_link":false,"pre_unlink":false,"run_exports":{},"subdirs":["linux-64","osx-arm64"],"summary":"Medical Image Registration ToolKit (with Viewer)","text_prefix":true,"timestamp":1774054297,"version":"2024.03.20"}},"subdirs":["linux-64","noarch","osx-arm64"]}
